vecmap/__init__.py
vecmap/applications/__init__.py
vecmap/applications/barcode.py
vecmap/applications/crispr.py
vecmap/cli/__init__.py
vecmap/cli/main.py
vecmap/core/__init__.py
vecmap/core/mapper.py
vecmap-1.0.0.dist-info/licenses/LICENSE
vecmap-1.0.0.dist-info/METADATA
vecmap-1.0.0.dist-info/WHEEL
vecmap-1.0.0.dist-info/entry_points.txt
vecmap-1.0.0.dist-info/top_level.txt
vecmap-1.0.0.dist-info/RECORD
