Metadata-Version: 2.4
Name: vecmap
Version: 1.0.0
Summary: Ultrafast exact sequence matching in pure Python using NumPy vectorization
Home-page: https://github.com/the-jordan-lab/VecMap
Author: James M. Jordan
Author-email: "James M. Jordan" <jjordan@bio.fsu.edu>
Maintainer-email: "James M. Jordan" <jjordan@bio.fsu.edu>
License-Expression: MIT
Project-URL: Homepage, https://github.com/the-jordan-lab/VecMap
Project-URL: Bug Tracker, https://github.com/the-jordan-lab/VecMap/issues
Project-URL: Documentation, https://github.com/the-jordan-lab/VecMap/blob/main/README.md
Keywords: bioinformatics,sequence alignment,CRISPR,vectorization,exact matching
Classifier: Development Status :: 4 - Beta
Classifier: Intended Audience :: Science/Research
Classifier: Programming Language :: Python :: 3
Classifier: Programming Language :: Python :: 3.9
Classifier: Programming Language :: Python :: 3.10
Classifier: Programming Language :: Python :: 3.11
Classifier: Programming Language :: Python :: 3.12
Classifier: Topic :: Scientific/Engineering :: Bio-Informatics
Requires-Python: >=3.9
License-File: LICENSE
Requires-Dist: numpy>=1.20.0
Provides-Extra: dev
Requires-Dist: pytest>=6.0; extra == "dev"
Requires-Dist: pytest-cov>=2.0; extra == "dev"
Requires-Dist: black>=22.0; extra == "dev"
Requires-Dist: flake8>=4.0; extra == "dev"
Provides-Extra: viz
Requires-Dist: matplotlib>=3.5.0; extra == "viz"
Requires-Dist: seaborn>=0.11.0; extra == "viz"
Requires-Dist: pandas>=1.3.0; extra == "viz"
Dynamic: author
Dynamic: home-page
Dynamic: license-file
Dynamic: requires-python
